Metadata-Version: 2.1
Name: web3lib
Version: 6.3.0
Summary: web3.py
Home-page: https://github.com/ethereum/web3.py
Author: Piper Merriam
Author-email: pipermerriam@gmail.com
License: MIT
Keywords: ethereum
Classifier: Development Status :: 5 - Production/Stable
Classifier: Intended Audience :: Developers
Classifier: License :: OSI Approved :: MIT License
Classifier: Natural Language :: English
Classifier: Programming Language :: Python :: 3
Classifier: Programming Language :: Python :: 3.7
Classifier: Programming Language :: Python :: 3.8
Classifier: Programming Language :: Python :: 3.9
Classifier: Programming Language :: Python :: 3.10
Classifier: Programming Language :: Python :: 3.11
Requires-Python: >=3.7.2
License-File: LICENSE
Requires-Dist: aiohttp (>=3.7.4.post0)
Requires-Dist: eth-abi (>=4.0.0)
Requires-Dist: eth-acount (>=0.8.0)
Requires-Dist: eth-hash[pycryptodome] (>=0.5.1)
Requires-Dist: eth-typing (>=3.0.0)
Requires-Dist: eth-utils (>=2.1.0)
Requires-Dist: hexbytes (>=0.1.0)
Requires-Dist: jsonschema (>=4.0.0)
Requires-Dist: lru-dict (>=1.1.6)
Requires-Dist: protobuf (>=4.21.6)
Requires-Dist: requests (>=2.16.0)
Requires-Dist: websockets (>=10.0.0)
Requires-Dist: pywin32 (>=223) ; platform_system == "Windows"
Requires-Dist: typing-extensions (<5,>=3.7.4.1) ; python_version < "3.8"
Provides-Extra: dev
Requires-Dist: eth-tester[py-evm] (==v0.8.0-b.3) ; extra == 'dev'
Requires-Dist: py-geth (>=3.11.0) ; extra == 'dev'
Requires-Dist: black (>=22.1.0) ; extra == 'dev'
Requires-Dist: flake8 (==3.8.3) ; extra == 'dev'
Requires-Dist: isort (>=5.11.0) ; extra == 'dev'
Requires-Dist: mypy (==0.910) ; extra == 'dev'
Requires-Dist: types-setuptools (>=57.4.4) ; extra == 'dev'
Requires-Dist: types-requests (>=2.26.1) ; extra == 'dev'
Requires-Dist: types-protobuf (==3.19.13) ; extra == 'dev'
Requires-Dist: sphinx (>=5.3.0) ; extra == 'dev'
Requires-Dist: sphinx-rtd-theme (>=1.0.0) ; extra == 'dev'
Requires-Dist: towncrier (<22,>=21) ; extra == 'dev'
Requires-Dist: ipfshttpclient (==0.8.0a2) ; extra == 'dev'
Requires-Dist: bumpversion ; extra == 'dev'
Requires-Dist: flaky (>=3.7.0) ; extra == 'dev'
Requires-Dist: hypothesis (>=3.31.2) ; extra == 'dev'
Requires-Dist: pytest (>=7.0.0) ; extra == 'dev'
Requires-Dist: pytest-asyncio (>=0.18.1) ; extra == 'dev'
Requires-Dist: pytest-mock (>=1.10) ; extra == 'dev'
Requires-Dist: pytest-watch (>=4.2) ; extra == 'dev'
Requires-Dist: pytest-xdist (>=1.29) ; extra == 'dev'
Requires-Dist: setuptools (>=38.6.0) ; extra == 'dev'
Requires-Dist: tox (>=3.18.0) ; extra == 'dev'
Requires-Dist: tqdm (>4.32) ; extra == 'dev'
Requires-Dist: twine (>=1.13) ; extra == 'dev'
Requires-Dist: pluggy (==0.13.1) ; extra == 'dev'
Requires-Dist: when-changed (>=0.3.0) ; extra == 'dev'
Requires-Dist: build (>=0.9.0) ; extra == 'dev'
Requires-Dist: importlib-metadata (<5.0) ; (python_version < "3.8") and extra == 'dev'
Provides-Extra: docs
Requires-Dist: sphinx (>=5.3.0) ; extra == 'docs'
Requires-Dist: sphinx-rtd-theme (>=1.0.0) ; extra == 'docs'
Requires-Dist: towncrier (<22,>=21) ; extra == 'docs'
Provides-Extra: ipfs
Requires-Dist: ipfshttpclient (==0.8.0a2) ; extra == 'ipfs'
Provides-Extra: linter
Requires-Dist: black (>=22.1.0) ; extra == 'linter'
Requires-Dist: flake8 (==3.8.3) ; extra == 'linter'
Requires-Dist: isort (>=5.11.0) ; extra == 'linter'
Requires-Dist: mypy (==0.910) ; extra == 'linter'
Requires-Dist: types-setuptools (>=57.4.4) ; extra == 'linter'
Requires-Dist: types-requests (>=2.26.1) ; extra == 'linter'
Requires-Dist: types-protobuf (==3.19.13) ; extra == 'linter'
Provides-Extra: tester
Requires-Dist: eth-tester[py-evm] (==v0.8.0-b.3) ; extra == 'tester'
Requires-Dist: py-geth (>=3.11.0) ; extra == 'tester'
